m2isar/__init__.py
m2isar/backends/__init__.py
m2isar/backends/coverage/__init__.py
m2isar/backends/coverage/coverage_dbg.py
m2isar/backends/coverage/coverage_lcov.py
m2isar/backends/coverage/id_transform.py
m2isar/backends/coverage/utils.py
m2isar/backends/disass/__init__.py
m2isar/backends/disass/disass.py
m2isar/backends/etiss/README.md
m2isar/backends/etiss/__init__.py
m2isar/backends/etiss/architecture_writer.py
m2isar/backends/etiss/instruction_generator.py
m2isar/backends/etiss/instruction_transform.py
m2isar/backends/etiss/instruction_utils.py
m2isar/backends/etiss/instruction_writer.py
m2isar/backends/etiss/pickle_writer.py
m2isar/backends/etiss/replacements.py
m2isar/backends/etiss/writer.py
m2isar/backends/etiss/templates/__init__.py
m2isar/backends/etiss/templates/etiss_arch_cmake.mako
m2isar/backends/etiss/templates/etiss_arch_cpp.mako
m2isar/backends/etiss/templates/etiss_arch_gdbcore.mako
m2isar/backends/etiss/templates/etiss_arch_h.mako
m2isar/backends/etiss/templates/etiss_arch_lib.mako
m2isar/backends/etiss/templates/etiss_arch_specific_cpp.mako
m2isar/backends/etiss/templates/etiss_arch_specific_h.mako
m2isar/backends/etiss/templates/etiss_arch_struct.mako
m2isar/backends/etiss/templates/etiss_function.mako
m2isar/backends/etiss/templates/etiss_function_header.mako
m2isar/backends/etiss/templates/etiss_function_set_footer.mako
m2isar/backends/etiss/templates/etiss_function_set_header.mako
m2isar/backends/etiss/templates/etiss_functions_c.mako
m2isar/backends/etiss/templates/etiss_instruction.mako
m2isar/backends/etiss/templates/etiss_instruction_callback.mako
m2isar/backends/etiss/templates/etiss_instruction_set.mako
m2isar/backends/isa_manual/.gitignore
m2isar/backends/isa_manual/README.md
m2isar/backends/isa_manual/__init__.py
m2isar/backends/isa_manual/package.json
m2isar/backends/isa_manual/render.sh
m2isar/backends/isa_manual/utils.py
m2isar/backends/isa_manual/visitor.py
m2isar/backends/isa_manual/writer.py
m2isar-0.0.6.dist-info/licenses/LICENSE
m2isar-0.0.6.dist-info/METADATA
m2isar-0.0.6.dist-info/WHEEL
m2isar-0.0.6.dist-info/entry_points.txt
m2isar-0.0.6.dist-info/top_level.txt
m2isar-0.0.6.dist-info/RECORD
