Metadata-Version: 2.4
Name: m2isar
Version: 0.0.6
Summary: CoreDSL2 Parser with backend to generate simulation code for the ETISS instruction set simulator
Author: Karsten Emrich
Author-email: Philipp van Kempen <philipp.van-kempen@tum.de>
Maintainer-email: Philipp van Kempen <philipp.van-kempen@tum.de>
License: Apache-2.0
Project-URL: Homepage, https://tum-ei-eda.github.io/M2-ISA-R
Project-URL: Documentation, https://tum-ei-eda.github.io/M2-ISA-R
Project-URL: Repository, https://github.com/tum-ei-eda/M2-ISA-R.git
Project-URL: Bug Tracker, https://github.com/tum-ei-eda/M2-ISA-R/issues
Requires-Python: >=3.8
License-File: LICENSE
Requires-Dist: mako
Requires-Dist: antlr4-python3-runtime==4.13.1
Requires-Dist: tqdm
Dynamic: license-file
